openlut/ColMap.py
openlut/ColMat.py
openlut/Func.py
openlut/LUT.py
openlut/Transform.py
openlut/Viewer.py
openlut/__init__.py
openlut/gamma.py
openlut/gamut.py
openlut/main.py
openlut/lib/__init__.py
openlut/lib/files.py
openlut/lib/olOpt.cp37-win32.pyd
openlut-0.2.7.dist-info/METADATA
openlut-0.2.7.dist-info/RECORD
openlut-0.2.7.dist-info/WHEEL
openlut-0.2.7.dist-info/top_level.txt
