Metadata-Version: 2.1
Name: openlut
Version: 0.2.7
Summary: OpenLUT is a practical color management library.
Home-page: https://www.github.com/so-rose/openlut
Author: Sofus Rose
Author-email: sofus@sofusrose.com
License: MIT License
Keywords: color,image,images,processing
Platform: UNKNOWN
Classifier: Development Status :: 3 - Alpha
Classifier: License :: OSI Approved :: MIT License
Classifier: Operating System :: Unix
Classifier: Operating System :: POSIX
Classifier: Programming Language :: Python :: 3
Requires-Dist: pip
Requires-Dist: setuptools
Requires-Dist: wheel
Requires-Dist: virtualenv
Requires-Dist: twine
Requires-Dist: pybind11
Requires-Dist: sphinx
Requires-Dist: sphinx-rtd-theme
Requires-Dist: pyinstaller
Requires-Dist: numpy
Requires-Dist: pygame
Requires-Dist: PyOpenGL
Requires-Dist: scipy
Requires-Dist: Wand
Requires-Dist: setuptools
Requires-Dist: pybind11
Requires-Dist: wheel
Requires-Dist: setuptools
Requires-Dist: sphinx
Requires-Dist: sphinx-rtd-theme
